cloud_optimized_dicom/__init__.py
cloud_optimized_dicom/append.py
cloud_optimized_dicom/cod_object.py
cloud_optimized_dicom/config.py
cloud_optimized_dicom/custom_offset_tables.py
cloud_optimized_dicom/dicomweb.py
cloud_optimized_dicom/errors.py
cloud_optimized_dicom/hints.py
cloud_optimized_dicom/instance.py
cloud_optimized_dicom/instance_metadata.py
cloud_optimized_dicom/locker.py
cloud_optimized_dicom/metrics.py
cloud_optimized_dicom/query_parsing.py
cloud_optimized_dicom/series_metadata.py
cloud_optimized_dicom/thumbnail.py
cloud_optimized_dicom/utils.py
cloud_optimized_dicom/virtual_file.py
cloud_optimized_dicom/tests/__init__.py
cloud_optimized_dicom/tests/test_appender.py
cloud_optimized_dicom/tests/test_cod_object.py
cloud_optimized_dicom/tests/test_concat.py
cloud_optimized_dicom/tests/test_custom_offset_tables.py
cloud_optimized_dicom/tests/test_dicomweb.py
cloud_optimized_dicom/tests/test_error_log.py
cloud_optimized_dicom/tests/test_hashed_uids.py
cloud_optimized_dicom/tests/test_hints.py
cloud_optimized_dicom/tests/test_instance.py
cloud_optimized_dicom/tests/test_locking.py
cloud_optimized_dicom/tests/test_metadata_serialization.py
cloud_optimized_dicom/tests/test_pydicom.py
cloud_optimized_dicom/tests/test_thumbnail.py
cloud_optimized_dicom/tests/test_truncate.py
cloud_optimized_dicom/tests/test_virtual_file.py
cloud_optimized_dicom-0.2.0.dist-info/licenses/LICENSE
cloud_optimized_dicom-0.2.0.dist-info/METADATA
cloud_optimized_dicom-0.2.0.dist-info/WHEEL
cloud_optimized_dicom-0.2.0.dist-info/top_level.txt
cloud_optimized_dicom-0.2.0.dist-info/RECORD
