Metadata-Version: 2.4
Name: cloud-optimized-dicom
Version: 0.2.0
Summary: A library for efficiently storing and interacting with DICOM files in the cloud
Author-email: Cal Nightingale <cal@gradienthealth.io>
License-Expression: MIT
Requires-Python: >=3.8
License-File: LICENSE
Requires-Dist: smart-open==7.0.4
Requires-Dist: ratarmountcore==0.7.1
Requires-Dist: numpy
Requires-Dist: google-cloud-storage==2.19.0
Requires-Dist: apache-beam[gcp]==2.63.0
Requires-Dist: filetype==1.2.0
Requires-Dist: pylibjpeg==2.0.1
Requires-Dist: pylibjpeg-libjpeg==2.3.0
Requires-Dist: pylibjpeg-openjpeg==2.4.0
Requires-Dist: pydicom3>=3.1.0
Requires-Dist: opencv-python-headless==4.11.0.86
Requires-Dist: ffmpeg-python==0.2.0
Requires-Dist: zstandard>=0.24.0
Requires-Dist: urllib3<2.6.0,>=2.0.0
Provides-Extra: test
Requires-Dist: pydicom==2.3.0; extra == "test"
Requires-Dist: matplotlib; extra == "test"
Provides-Extra: dev
Requires-Dist: pre-commit>=3.0.0; extra == "dev"
Requires-Dist: pydicom==2.3.0; extra == "dev"
Requires-Dist: matplotlib; extra == "dev"
Dynamic: license-file
